{"columns": {"what": [0, "Marauder 1", "Marauder 2", "Marauder 3", "Marauder 4", "Marauder 5", "Marauder 6", "Marauder 7", "Marauder 8", "Marauder 9", "Marauder 10", "Reward 1", "Reward 2", "Reward 3", "Reward 4", "Reward 5"], "level": ["Min", 1, 41, 61, 91, 111, 131, 146, 181, 201, 241, 1, 1, 50, 70, 90], "_cpzh4": ["Max", 40, 60, 90, 110, 130, 145, 180, 200, 240, 999, 50, 999, 999, 999, 999], "weight": [0, 3500, 4500, 3500, 3750, 3750, 3750, 3750, 3750, 3750, 3750, 8000, 6000, 5000, 4000, 2000], "ratesfordifferentlevelsspans": ["1 - 40", "20.00%", 0, 0, 0, 0, 0, 0, 0, 0, 0, "45.71%", "34.29%", 0, 0, 0], "_ciyn3": ["41 - 49", "24.32%", "43.24%", "32.43%"], "_ckd7g": [50, "19.15%", "34.04%", "25.53%", "21.28%"], "_clrrx": ["51 - 60", "29.03%", "38.71%", "32.26%"], "_cyevm": ["61 - 69", "24.14%", "41.38%", "34.48%"], "_cztg3": ["70 - 89", "18.92%", "32.43%", "27.03%", "21.62%"], "_d180g": [90, "17.07%", "29.27%", "24.39%", "19.51%", "9.76%"], "_d2mkx": ["91+", "18.07%", "18.07%", "18.07%", "18.07%", "18.07%", "18.07%", "18.07%", "28.92%", "24.10%", "19.28%", "9.64%"], "finalreward": ["Gems", 40, 80, 160, 320, 320, 320, 320, 320, 320, 320, 0, 0, 0, 0, 0], "coefficient": [0, 1000, 800, 560, 300, 300, 300, 220, 160, 120, 100, 0, 0, 0, 0, 0], "marauderlineup": ["id 1", 6001, 6006, 0, 6011, 6012, 6013, 6014, 6015, 6016, 6017, 0, 0, 0, 0, 0], "_cx0b9": ["id 3", 6002, 6007, 6009], "_d9ney": ["id 4", 6003], "_db1zf": ["id 5", 6004], "_dcgjs": ["id 6", 6005, 6008, 6010], "_ddv49": ["Front 1", "40lvl Boss 3* Frey", "60lvl Boss 4* Nightmare Knight", "120lvl Boss 5* Dark Arthindol", "130lvl Boss 5* Malassa", "140lvl Boss 5* Margaret", "160lvl Boss 5* Walter", "250lvl Boss 10* OD-01", "300lvl Boss 10* Kamath", "320lvl Boss 10* Sigmund"], "_d415a": ["Back 3", "40lvl 3* Shirley", "60lvl Boss 4* Time Mage", "90lvl Boss 5* Demon Hunter"], "_d5fpr": ["Back 4", "40lvl 3* Sybil"], "_d6ua4": ["Back 5", "40lvl 3* Tara's Servant"], "_d88ul": ["Back 6", "40lvl 3* Succube", "60lvl Boss 4* Wind Walker", "90lvl Boss 5* Aidan"]}, "rows": [{"what": 0, "level": "Min", "_cpzh4": "Max", "weight": 0, "ratesfordifferentlevelsspans": "1 - 40", "_ciyn3": "41 - 49", "_ckd7g": 50, "_clrrx": "51 - 60", "_cyevm": "61 - 69", "_cztg3": "70 - 89", "_d180g": 90, "_d2mkx": "91+", "finalreward": "Gems", "coefficient": 0, "marauderlineup": "id 1", "_cx0b9": "id 3", "_d9ney": "id 4", "_db1zf": "id 5", "_dcgjs": "id 6", "_ddv49": "Front 1", "_d415a": "Back 3", "_d5fpr": "Back 4", "_d6ua4": "Back 5", "_d88ul": "Back 6"}, {"what": "Marauder 1", "level": 1, "_cpzh4": 40, "weight": 3500, "ratesfordifferentlevelsspans": "20.00%", "finalreward": 40, "coefficient": 1000, "marauderlineup": 6001, "_cx0b9": 6002, "_d9ney": 6003, "_db1zf": 6004, "_dcgjs": 6005, "_ddv49": "40lvl Boss 3* Frey", "_d415a": "40lvl 3* Shirley", "_d5fpr": "40lvl 3* Sybil", "_d6ua4": "40lvl 3* Tara's Servant", "_d88ul": "40lvl 3* Succube"}, {"what": "Marauder 2", "level": 41, "_cpzh4": 60, "weight": 4500, "ratesfordifferentlevelsspans": 0, "_ciyn3": "24.32%", "_ckd7g": "19.15%", "_clrrx": "29.03%", "finalreward": 80, "coefficient": 800, "marauderlineup": 6006, "_cx0b9": 6007, "_dcgjs": 6008, "_ddv49": "60lvl Boss 4* Nightmare Knight", "_d415a": "60lvl Boss 4* Time Mage", "_d88ul": "60lvl Boss 4* Wind Walker"}, {"what": "Marauder 3", "level": 61, "_cpzh4": 90, "weight": 3500, "ratesfordifferentlevelsspans": 0, "_cyevm": "24.14%", "_cztg3": "18.92%", "_d180g": "17.07%", "finalreward": 160, "coefficient": 560, "marauderlineup": 0, "_cx0b9": 6009, "_dcgjs": 6010, "_d415a": "90lvl Boss 5* Demon Hunter", "_d88ul": "90lvl Boss 5* Aidan"}, {"what": "Marauder 4", "level": 91, "_cpzh4": 110, "weight": 3750, "ratesfordifferentlevelsspans": 0, "_d2mkx": "18.07%", "finalreward": 320, "coefficient": 300, "marauderlineup": 6011, "_ddv49": "120lvl Boss 5* Dark Arthindol"}, {"what": "Marauder 5", "level": 111, "_cpzh4": 130, "weight": 3750, "ratesfordifferentlevelsspans": 0, "_d2mkx": "18.07%", "finalreward": 320, "coefficient": 300, "marauderlineup": 6012, "_ddv49": "130lvl Boss 5* Malassa"}, {"what": "Marauder 6", "level": 131, "_cpzh4": 145, "weight": 3750, "ratesfordifferentlevelsspans": 0, "_d2mkx": "18.07%", "finalreward": 320, "coefficient": 300, "marauderlineup": 6013, "_ddv49": "140lvl Boss 5* Margaret"}, {"what": "Marauder 7", "level": 146, "_cpzh4": 180, "weight": 3750, "ratesfordifferentlevelsspans": 0, "_d2mkx": "18.07%", "finalreward": 320, "coefficient": 220, "marauderlineup": 6014, "_ddv49": "160lvl Boss 5* Walter"}, {"what": "Marauder 8", "level": 181, "_cpzh4": 200, "weight": 3750, "ratesfordifferentlevelsspans": 0, "_d2mkx": "18.07%", "finalreward": 320, "coefficient": 160, "marauderlineup": 6015, "_ddv49": "250lvl Boss 10* OD-01"}, {"what": "Marauder 9", "level": 201, "_cpzh4": 240, "weight": 3750, "ratesfordifferentlevelsspans": 0, "_d2mkx": "18.07%", "finalreward": 320, "coefficient": 120, "marauderlineup": 6016, "_ddv49": "300lvl Boss 10* Kamath"}, {"what": "Marauder 10", "level": 241, "_cpzh4": 999, "weight": 3750, "ratesfordifferentlevelsspans": 0, "_d2mkx": "18.07%", "finalreward": 320, "coefficient": 100, "marauderlineup": 6017, "_ddv49": "320lvl Boss 10* Sigmund"}, {"what": "Reward 1", "level": 1, "_cpzh4": 50, "weight": 8000, "ratesfordifferentlevelsspans": "45.71%", "_ciyn3": "43.24%", "_ckd7g": "34.04%", "finalreward": 0, "coefficient": 0, "marauderlineup": 0}, {"what": "Reward 2", "level": 1, "_cpzh4": 999, "weight": 6000, "ratesfordifferentlevelsspans": "34.29%", "_ciyn3": "32.43%", "_ckd7g": "25.53%", "_clrrx": "38.71%", "_cyevm": "41.38%", "_cztg3": "32.43%", "_d180g": "29.27%", "_d2mkx": "28.92%", "finalreward": 0, "coefficient": 0, "marauderlineup": 0}, {"what": "Reward 3", "level": 50, "_cpzh4": 999, "weight": 5000, "ratesfordifferentlevelsspans": 0, "_ckd7g": "21.28%", "_clrrx": "32.26%", "_cyevm": "34.48%", "_cztg3": "27.03%", "_d180g": "24.39%", "_d2mkx": "24.10%", "finalreward": 0, "coefficient": 0, "marauderlineup": 0}, {"what": "Reward 4", "level": 70, "_cpzh4": 999, "weight": 4000, "ratesfordifferentlevelsspans": 0, "_cztg3": "21.62%", "_d180g": "19.51%", "_d2mkx": "19.28%", "finalreward": 0, "coefficient": 0, "marauderlineup": 0}, {"what": "Reward 5", "level": 90, "_cpzh4": 999, "weight": 2000, "ratesfordifferentlevelsspans": 0, "_d180g": "9.76%", "_d2mkx": "9.64%", "finalreward": 0, "coefficient": 0, "marauderlineup": 0}]}